{
  "segment": "Healthcare Facilities - Decision Makers with Emails",
  "target_area": "Las Vegas / Henderson / North Las Vegas, NV",
  "generated": "2026-02-03",
  "source": "LinkedIn profiles, Google search, CMS Medicare database, hospital websites, ZoomInfo snippets, AirNav data, UMC board minutes",
  "email_verification_notes": {
    "verified": "Email confirmed via public source (website, document, or database)",
    "pattern_confirmed": "Domain email pattern verified via known addresses; name applied to pattern",
    "domain_only": "Company email domain known; contact name identified but email constructed from pattern only"
  },
  "email_patterns_confirmed": {
    "umcsn.com": {
      "format": "firstname.lastname@umcsn.com",
      "confirmed_by": "michael.langley@umcsn.com (AirNav.com), s***@umcsn.com for Stephanie Ortiz (ZoomInfo), feedback@umcsn.com, accommodation.request@umcsn.com"
    },
    "uhsinc.com": {
      "format": "firstname.lastname@uhsinc.com",
      "confirmed_by": "NVCBO@uhsinc.com (Nevada Central Business Office - found on Henderson Hospital and Centennial Hills Hospital websites)"
    },
    "davita.com": {
      "format": "firstname.lastname@davita.com",
      "confirmed_by": "Standard DaVita corporate format, publicly known"
    },
    "dignityhealth.org": {
      "format": "firstname.lastname@dignityhealth.org",
      "confirmed_by": "Standard Dignity Health/CommonSpirit format, publicly known"
    },
    "acadiahealthcare.com": {
      "format": "firstname.lastname@acadiahealthcare.com",
      "confirmed_by": "Standard Acadia Healthcare format for Seven Hills BH"
    }
  },
  "prospects": [
    {
      "id": 1,
      "company": "University Medical Center (UMC)",
      "facility_type": "Level I Trauma Center / Public Hospital",
      "address": "1800 W Charleston Blvd, Las Vegas, NV 89102",
      "parent_system": "Clark County (Government)",
      "bed_count": 564,
      "contact_name": "Tony Marinello",
      "contact_title": "Chief Operating Officer",
      "email": "tony.marinello@umcsn.com",
      "email_status": "pattern_confirmed",
      "phone": "(702) 383-2000",
      "linkedin": null,
      "employee_count": "3000-4000",
      "vending_score": "A+",
      "notes": "COO is best initial contact for vending/amenity services at UMC. Name confirmed via UMC governing board minutes (Feb 2025). Public hospital = may require RFP process. Biggest potential contract in the valley. 24/7 ER, massive foot traffic.",
      "apollo_enriched": false,
      "enriched_at": "2026-02-03T11:53:11.361Z",
      "priority": "high",
      "priority_reasons": [
        "4000+ people/units",
        "24/7 or captive audience"
      ],
      "enrich_score": 65
    },
    {
      "id": 2,
      "company": "University Medical Center (UMC)",
      "facility_type": "Level I Trauma Center / Public Hospital",
      "address": "1800 W Charleston Blvd, Las Vegas, NV 89102",
      "parent_system": "Clark County (Government)",
      "bed_count": 564,
      "contact_name": "Stephanie Ortiz",
      "contact_title": "Project Manager, Facilities",
      "email": "stephanie.ortiz@umcsn.com",
      "email_status": "verified",
      "phone": "(702) 383-2000",
      "linkedin": null,
      "employee_count": "3000-4000",
      "vending_score": "A+",
      "notes": "Direct facilities contact at UMC. Email confirmed via ZoomInfo (s***@umcsn.com). Project Manager in Facilities Dept - ideal contact for smart market placement discussions.",
      "priority": "high",
      "priority_reasons": [
        "4000+ people/units",
        "24/7 or captive audience"
      ],
      "enrich_score": 65
    },
    {
      "id": 3,
      "company": "University Medical Center (UMC)",
      "facility_type": "Level I Trauma Center / Public Hospital",
      "address": "1800 W Charleston Blvd, Las Vegas, NV 89102",
      "parent_system": "Clark County (Government)",
      "bed_count": 564,
      "contact_name": "Michael Langley",
      "contact_title": "Facilities Operations",
      "email": "michael.langley@umcsn.com",
      "email_status": "verified",
      "phone": "(702) 383-2007",
      "linkedin": null,
      "employee_count": "3000-4000",
      "vending_score": "A+",
      "notes": "Email CONFIRMED on AirNav.com heliport listing. Alt phone: (702) 972-1618. Facilities operations contact - good entry point for vending/amenity discussions.",
      "priority": "high",
      "priority_reasons": [
        "4000+ people/units",
        "24/7 or captive audience"
      ],
      "enrich_score": 65
    },
    {
      "id": 4,
      "company": "Henderson Hospital",
      "facility_type": "Acute Care Hospital",
      "address": "1050 W Galleria Dr, Henderson, NV 89011",
      "parent_system": "Valley Health System / Universal Health Services (UHS)",
      "bed_count": 166,
      "contact_name": "Nevada Central Business Office",
      "contact_title": "Vendor Inquiries / Business Office",
      "email": "NVCBO@uhsinc.com",
      "email_status": "verified",
      "phone": "(702) 894-5700 ext 7",
      "linkedin": null,
      "employee_count": "500-800",
      "vending_score": "A+",
      "notes": "NVCBO@uhsinc.com confirmed on Henderson Hospital and Centennial Hills Hospital websites. Start here for vendor approval process across ALL Valley Health System hospitals (6 hospitals + 7 freestanding ERs). Henderson is HOME BASE for Kande VendTech.",
      "priority": "high",
      "priority_reasons": [
        "800+ people/units",
        "24/7 or captive audience"
      ],
      "enrich_score": 33
    },
    {
      "id": 5,
      "company": "Valley Health System (Regional HQ)",
      "facility_type": "Hospital System Corporate Office",
      "address": "8801 W Sahara Ave, Las Vegas, NV 89117",
      "parent_system": "Universal Health Services (UHS)",
      "bed_count": null,
      "contact_name": "Karla Perez",
      "contact_title": "Regional Vice President",
      "email": "karla.perez@uhsinc.com",
      "email_status": "pattern_confirmed",
      "phone": "(702) 388-4000",
      "linkedin": null,
      "employee_count": "8000+ (system-wide)",
      "vending_score": "A+",
      "notes": "Regional VP named in Nevada Hospital Association press release about Valley Health System. System-wide deal target: 6 acute care hospitals + West Henderson Hospital (newest, opened 2024) + 7 freestanding ERs + Spring Mountain Treatment Center. UHS email format confirmed via NVCBO@uhsinc.com.",
      "apollo_enriched": false,
      "enriched_at": "2026-02-03T11:53:11.694Z",
      "priority": "high",
      "priority_reasons": [
        "8000+ people/units",
        "24/7 or captive audience",
        "new build / no vendor",
        "portfolio / multi-property leverage"
      ],
      "enrich_score": 110
    },
    {
      "id": 6,
      "company": "Centennial Hills Hospital Medical Center",
      "facility_type": "Acute Care Hospital",
      "address": "6900 N Durango Dr, Las Vegas, NV 89149",
      "parent_system": "Valley Health System / UHS",
      "bed_count": 339,
      "contact_name": "Director of Facilities (via NVCBO)",
      "contact_title": "Director of Facilities / Plant Operations",
      "email": "NVCBO@uhsinc.com",
      "email_status": "verified",
      "phone": "(702) 835-9700",
      "linkedin": null,
      "employee_count": "800-1200",
      "vending_score": "A+",
      "notes": "Route through NVCBO for vendor access. 339 beds, 354K sq ft. Opened 2008. Active facility management hiring (LinkedIn posting for Manager of Facility Management). Large campus = multiple machine placement opportunities.",
      "priority": "high",
      "priority_reasons": [
        "1200+ people/units",
        "24/7 or captive audience"
      ],
      "enrich_score": 37
    },
    {
      "id": 7,
      "company": "Summerlin Hospital Medical Center",
      "facility_type": "Acute Care Hospital",
      "address": "657 N Town Center Dr, Las Vegas, NV 89144",
      "parent_system": "Valley Health System / UHS",
      "bed_count": 496,
      "contact_name": "Director of Facilities (via NVCBO)",
      "contact_title": "Director of Facilities",
      "email": "NVCBO@uhsinc.com",
      "email_status": "verified",
      "phone": "(702) 233-7000",
      "linkedin": null,
      "employee_count": "1200-1800",
      "vending_score": "A+",
      "notes": "Summerlin = wealthiest area of Las Vegas. Premium vending products command higher prices. Bundle with other UHS hospitals for system-wide deal.",
      "priority": "high",
      "priority_reasons": [
        "1800+ people/units",
        "24/7 or captive audience",
        "portfolio / multi-property leverage"
      ],
      "enrich_score": 53
    },
    {
      "id": 8,
      "company": "Spring Valley Hospital Medical Center",
      "facility_type": "Acute Care Hospital",
      "address": "5400 S Rainbow Blvd, Las Vegas, NV 89118",
      "parent_system": "Valley Health System / UHS",
      "bed_count": 364,
      "contact_name": "Director of Facilities (via NVCBO)",
      "contact_title": "Director of Facilities",
      "email": "NVCBO@uhsinc.com",
      "email_status": "verified",
      "phone": "(702) 853-3000",
      "linkedin": null,
      "employee_count": "800-1200",
      "vending_score": "A",
      "notes": "Southwest LV location. Part of UHS system-wide opportunity.",
      "priority": "high",
      "priority_reasons": [
        "1200+ people/units",
        "24/7 or captive audience",
        "portfolio / multi-property leverage"
      ],
      "enrich_score": 47
    },
    {
      "id": 9,
      "company": "West Henderson Hospital",
      "facility_type": "Acute Care Hospital (NEW)",
      "address": "1171 W Horizon Ridge Pkwy, Henderson, NV 89012",
      "parent_system": "Valley Health System / UHS",
      "bed_count": 150,
      "contact_name": "Director of Facilities (via NVCBO)",
      "contact_title": "Director of Facilities",
      "email": "NVCBO@uhsinc.com",
      "email_status": "verified",
      "phone": "(702) 963-7000",
      "linkedin": null,
      "employee_count": "400-600",
      "vending_score": "A+",
      "notes": "NEWEST Valley Health System hospital (opened 2024). New facility = NO entrenched vending vendor. Henderson location = Kande home base. Priority target!",
      "priority": "high",
      "priority_reasons": [
        "600+ people/units",
        "24/7 or captive audience",
        "new build / no vendor",
        "entrenched vendor noted"
      ],
      "enrich_score": 56
    },
    {
      "id": 10,
      "company": "Sunrise Hospital and Medical Center",
      "facility_type": "Level II Trauma / Acute Care Hospital",
      "address": "3186 S Maryland Pkwy, Las Vegas, NV 89109",
      "parent_system": "HCA Healthcare (Sunrise Health System)",
      "bed_count": 688,
      "contact_name": "Director of Support Services",
      "contact_title": "Director of Support Services",
      "email": null,
      "email_status": "needs_research",
      "phone": "(702) 961-5000",
      "linkedin": null,
      "employee_count": "2000-3000",
      "vending_score": "A+",
      "notes": "Largest hospital in Nevada. HCA Healthcare may have existing national vending contracts. Check for local supplement opportunities. Break rooms, waiting areas, ER waiting room. HCA email domain: hcahealthcare.com",
      "priority": "high",
      "priority_reasons": [
        "3000+ people/units",
        "24/7 or captive audience"
      ],
      "enrich_score": 50
    },
    {
      "id": 11,
      "company": "MountainView Hospital",
      "facility_type": "Acute Care Hospital",
      "address": "3100 N Tenaya Way, Las Vegas, NV 89128",
      "parent_system": "HCA Healthcare (Sunrise Health System)",
      "bed_count": 425,
      "contact_name": "Manager of Facility Management (open position)",
      "contact_title": "Manager of Facility Management",
      "email": null,
      "email_status": "needs_research",
      "phone": "(702) 255-5000",
      "linkedin": "https://www.linkedin.com/jobs/view/manager-of-facility-management-at-mountainview-hospital-4346298925",
      "employee_count": "1200-1800",
      "vending_score": "A",
      "notes": "Currently hiring Manager of Facility Management (LinkedIn job posting Dec 2025). Good timing to approach - new facility manager will need vendors. HCA property.",
      "priority": "high",
      "priority_reasons": [
        "1800+ people/units",
        "24/7 or captive audience",
        "new build / no vendor"
      ],
      "enrich_score": 63
    },
    {
      "id": 12,
      "company": "Southern Hills Hospital & Medical Center",
      "facility_type": "Acute Care Hospital",
      "address": "9300 W Sunset Rd, Las Vegas, NV 89148",
      "parent_system": "HCA Healthcare (Sunrise Health System)",
      "bed_count": 252,
      "contact_name": "Manager of Facility Management (open position)",
      "contact_title": "Manager of Facility Management and Safety",
      "email": null,
      "email_status": "needs_research",
      "phone": "(702) 880-2100",
      "linkedin": "https://www.linkedin.com/jobs/view/manager-of-facility-management-and-safety-at-southern-hills-hospital-and-medical-center-4366675725",
      "employee_count": "800-1200",
      "vending_score": "A",
      "notes": "Also currently hiring Manager of Facility Management (LinkedIn Jan 2026). 80-bed behavioral health unit = secure area vending needs. Good time to pitch to incoming manager.",
      "priority": "high",
      "priority_reasons": [
        "1200+ people/units",
        "24/7 or captive audience"
      ],
      "enrich_score": 32
    },
    {
      "id": 13,
      "company": "Dignity Health - St. Rose Dominican, Siena Campus",
      "facility_type": "Acute Care Hospital",
      "address": "3001 St. Rose Pkwy, Henderson, NV 89052",
      "parent_system": "CommonSpirit Health / Dignity Health",
      "bed_count": 326,
      "contact_name": "Director of Facilities Management",
      "contact_title": "Director of Facilities Management",
      "email": null,
      "email_status": "domain_only",
      "phone": "(702) 616-5000",
      "linkedin": null,
      "employee_count": "1000-1500",
      "vending_score": "A",
      "notes": "Henderson location. Dignity Health email: @dignityhealth.org. Large campus. Bundle with Rose de Lima and San Martin campuses for triple deal. Henderson's only pediatric ER.",
      "priority": "high",
      "priority_reasons": [
        "1500+ people/units",
        "24/7 or captive audience"
      ],
      "enrich_score": 35
    },
    {
      "id": 14,
      "company": "Dignity Health - St. Rose Dominican, San Martin Campus",
      "facility_type": "Acute Care Hospital",
      "address": "8280 W Warm Springs Rd, Las Vegas, NV 89113",
      "parent_system": "CommonSpirit Health / Dignity Health",
      "bed_count": 266,
      "contact_name": "Director of Facilities Management",
      "contact_title": "Director of Facilities Management",
      "email": null,
      "email_status": "domain_only",
      "phone": "(702) 492-8000",
      "linkedin": null,
      "employee_count": "800-1200",
      "vending_score": "A",
      "notes": "Newsweek ranked #1 hospital in Nevada (2026). High prestige = high standards for vending quality. Dignity email: @dignityhealth.org.",
      "priority": "high",
      "priority_reasons": [
        "1200+ people/units",
        "24/7 or captive audience"
      ],
      "enrich_score": 32
    },
    {
      "id": 15,
      "company": "Seven Hills Behavioral Health Hospital",
      "facility_type": "Behavioral Health Hospital",
      "address": "3021 W Horizon Ridge Pkwy, Henderson, NV 89052",
      "parent_system": "Acadia Healthcare",
      "bed_count": 134,
      "contact_name": "Director of Facility Operations (hiring)",
      "contact_title": "Director-Facility Operations",
      "email": null,
      "email_status": "domain_only",
      "phone": "(702) 646-5000",
      "linkedin": "https://www.linkedin.com/jobs/view/director-facility-operations-at-seven-hills-behavioral-health-hospital-4365908215",
      "employee_count": "300-500",
      "vending_score": "A",
      "notes": "Henderson location! Currently hiring Director of Facility Operations (LinkedIn posting). Acadia Healthcare parent. Behavioral health = secure area, patients can't leave = captive audience for vending. Email domain: @acadiahealthcare.com",
      "priority": "high",
      "priority_reasons": [
        "500+ people/units",
        "24/7 or captive audience"
      ],
      "enrich_score": 25
    },
    {
      "id": 16,
      "company": "DaVita South Las Vegas Dialysis Center",
      "facility_type": "Dialysis Center",
      "address": "6330 S Pecos Rd #600, Las Vegas, NV 89120",
      "parent_system": "DaVita Kidney Care",
      "bed_count": null,
      "contact_name": "Wesley Molden",
      "contact_title": "Facility Administrator",
      "email": "wesley.molden@davita.com",
      "email_status": "pattern_confirmed",
      "phone": null,
      "linkedin": "https://www.linkedin.com/in/wesley-molden-b524b1188",
      "employee_count": "20-40",
      "vending_score": "B+",
      "notes": "Confirmed on LinkedIn: Facility Administrator of DaVita South Las Vegas Dialysis Center. Dialysis patients sit 3-4 hours per session, 3x/week = captive audience. DaVita has 15+ centers in Las Vegas metro. Win one = referral to others.",
      "apollo_enriched": false,
      "enriched_at": "2026-02-03T11:53:12.028Z",
      "priority": "high",
      "priority_reasons": [
        "24/7 or captive audience",
        "chain gateway (15+ locations)"
      ],
      "enrich_score": 45
    },
    {
      "id": 17,
      "company": "DaVita Las Vegas Dialysis (multiple locations)",
      "facility_type": "Dialysis Center",
      "address": "Various Las Vegas locations",
      "parent_system": "DaVita Kidney Care",
      "bed_count": null,
      "contact_name": "Laurence Fortes",
      "contact_title": "Facility Administrator",
      "email": "laurence.fortes@davita.com",
      "email_status": "pattern_confirmed",
      "phone": null,
      "linkedin": "https://www.linkedin.com/in/laurence-fortes-b76a3672",
      "employee_count": "20-40",
      "vending_score": "B+",
      "notes": "LinkedIn confirmed: Facility Administrator at DaVita Kidney Care, Las Vegas. DaVita email format: firstname.lastname@davita.com.",
      "apollo_enriched": false,
      "enriched_at": "2026-02-03T11:53:12.369Z",
      "priority": "high",
      "priority_reasons": [
        "24/7 or captive audience",
        "portfolio / multi-property leverage",
        "small (<50): 40"
      ],
      "enrich_score": 25
    },
    {
      "id": 18,
      "company": "DaVita Las Vegas Dialysis",
      "facility_type": "Dialysis Center",
      "address": "Various Las Vegas locations",
      "parent_system": "DaVita Kidney Care",
      "bed_count": null,
      "contact_name": "Angela Weinstock",
      "contact_title": "Facility Administrator (Group FA)",
      "email": "angela.weinstock@davita.com",
      "email_status": "pattern_confirmed",
      "phone": null,
      "linkedin": "https://www.linkedin.com/in/angela-weinstock-20b329138",
      "employee_count": "20-40 per center",
      "vending_score": "B+",
      "notes": "LinkedIn: DaVita Kidney Care Las Vegas since Aug 2023, appears to be Group FA overseeing multiple centers. Higher-level contact could unlock multiple locations.",
      "apollo_enriched": false,
      "enriched_at": "2026-02-03T11:53:12.699Z",
      "priority": "high",
      "priority_reasons": [
        "24/7 or captive audience",
        "portfolio / multi-property leverage",
        "small (<50): 40"
      ],
      "enrich_score": 25
    },
    {
      "id": 19,
      "company": "San Martin Senior Living",
      "facility_type": "Senior Living / Memory Care",
      "address": "Las Vegas, NV (San Martin area)",
      "parent_system": "Independent / Regional",
      "bed_count": null,
      "contact_name": "Christina Perez",
      "contact_title": "Executive Director",
      "email": null,
      "email_status": "needs_research",
      "phone": null,
      "linkedin": "https://www.linkedin.com/in/christina-perez-14442629",
      "employee_count": "50-80",
      "vending_score": "A-",
      "notes": "LinkedIn confirmed: Executive Director of San Martin Senior Living. Also manages Legacies at San Martin Memory Care. Senior living = staff, visitors, and mobile residents all need refreshment access.",
      "apollo_enriched": false,
      "enriched_at": "2026-02-03T11:53:13.037Z",
      "priority": "high",
      "priority_reasons": [
        "portfolio / multi-property leverage"
      ],
      "enrich_score": 11
    },
    {
      "id": 20,
      "company": "Cascade Living Group (Las Vegas property)",
      "facility_type": "Senior Living",
      "address": "Las Vegas, NV",
      "parent_system": "Cascade Living Group",
      "bed_count": null,
      "contact_name": "Alexia Smith, RFA",
      "contact_title": "Executive Director",
      "email": null,
      "email_status": "needs_research",
      "phone": null,
      "linkedin": "https://www.linkedin.com/in/alexia-smith-rfa-87a730158",
      "employee_count": "50-80",
      "vending_score": "A-",
      "notes": "Licensed Residential Facility Administrator. Executive Director in Las Vegas metro. Cascade Living Group = multi-facility operator, could be portfolio deal.",
      "apollo_enriched": false,
      "enriched_at": "2026-02-03T11:53:13.375Z",
      "priority": "high",
      "priority_reasons": [
        "portfolio / multi-property leverage"
      ],
      "enrich_score": 11
    },
    {
      "id": 21,
      "company": "Alorah Healthcare Las Vegas",
      "facility_type": "Skilled Nursing Facility (New Build)",
      "address": "Henderson/Las Vegas, NV",
      "parent_system": "Alorah Healthcare",
      "bed_count": null,
      "contact_name": "Dan Hills, LNHA",
      "contact_title": "Administrator and Project Manager",
      "email": null,
      "email_status": "needs_research",
      "phone": null,
      "linkedin": "https://www.linkedin.com/in/dan-hills-lnha-57722748",
      "employee_count": "80-120",
      "vending_score": "A",
      "notes": "Licensed NHA leading a NEW BUILD skilled nursing facility in Las Vegas. Henderson-based. New facility = no existing vendor. PRIORITY target - get in early before another vendor claims it.",
      "apollo_enriched": false,
      "enriched_at": "2026-02-03T11:53:13.709Z",
      "priority": "high",
      "priority_reasons": [
        "120+ people/units",
        "24/7 or captive audience",
        "new build / no vendor",
        "entrenched vendor noted"
      ],
      "enrich_score": 46
    },
    {
      "id": 22,
      "company": "Marquis Companies (Las Vegas)",
      "facility_type": "Senior Living / Skilled Nursing",
      "address": "Las Vegas, NV",
      "parent_system": "Marquis Companies",
      "bed_count": null,
      "contact_name": "Jacob Atwood",
      "contact_title": "Administrator",
      "email": null,
      "email_status": "needs_research",
      "phone": null,
      "linkedin": "https://www.linkedin.com/in/jacob-atwood-2463b140",
      "employee_count": "80-150",
      "vending_score": "A-",
      "notes": "Marquis Companies is a multi-state senior living operator. Jacob Atwood is Administrator in Las Vegas. National chain = potential for portfolio deal if Las Vegas location succeeds.",
      "apollo_enriched": false,
      "enriched_at": "2026-02-03T11:53:14.049Z",
      "priority": "high",
      "priority_reasons": [
        "150+ people/units",
        "portfolio / multi-property leverage"
      ],
      "enrich_score": 22
    },
    {
      "id": 23,
      "company": "Life Care Centers of America (Las Vegas)",
      "facility_type": "Skilled Nursing / Senior Living",
      "address": "Las Vegas, NV",
      "parent_system": "Life Care Centers of America",
      "bed_count": null,
      "contact_name": "Clarissa Dewese",
      "contact_title": "Executive Director",
      "email": null,
      "email_status": "needs_research",
      "phone": null,
      "linkedin": "https://www.linkedin.com/in/clarissa-dewese-633167140",
      "employee_count": "80-150",
      "vending_score": "A-",
      "notes": "Life Care Centers is one of largest SNF chains in US. Clarissa Dewese is Executive Director / Licensed Skilled Nursing Administrator in Las Vegas metro. Landing this account could open doors to 200+ Life Care locations nationally.",
      "apollo_enriched": false,
      "enriched_at": "2026-02-03T11:53:14.384Z",
      "priority": "high",
      "priority_reasons": [
        "150+ people/units"
      ],
      "enrich_score": 12
    },
    {
      "id": 24,
      "company": "Fundamental Healthcare (Las Vegas)",
      "facility_type": "Skilled Nursing Facility",
      "address": "Las Vegas, NV",
      "parent_system": "Fundamental",
      "bed_count": null,
      "contact_name": "Rhett Jensen",
      "contact_title": "Licensed Nursing Home Administrator",
      "email": null,
      "email_status": "needs_research",
      "phone": null,
      "linkedin": "https://www.linkedin.com/in/rhett-jensen-b77456133",
      "employee_count": "80-150",
      "vending_score": "A-",
      "notes": "Licensed NHA at Fundamental in Las Vegas. 24/7 staff = vending demand especially nights/weekends when cafeteria is closed.",
      "apollo_enriched": false,
      "enriched_at": "2026-02-03T11:53:14.716Z",
      "priority": "high",
      "priority_reasons": [
        "150+ people/units",
        "24/7 or captive audience"
      ],
      "enrich_score": 22
    },
    {
      "id": 25,
      "company": "NeuroRestorative (Las Vegas)",
      "facility_type": "Rehabilitation / Behavioral Health",
      "address": "Las Vegas, NV",
      "parent_system": "NeuroRestorative (Sevita)",
      "bed_count": null,
      "contact_name": "Misty Harvey",
      "contact_title": "Administrator",
      "email": null,
      "email_status": "needs_research",
      "phone": null,
      "linkedin": "https://www.linkedin.com/in/mistyharvey",
      "employee_count": "50-100",
      "vending_score": "B+",
      "notes": "NeuroRestorative provides brain injury and rehab services. Part of Sevita (formerly The MENTOR Network). Patients in long-term rehab = captive audience.",
      "apollo_enriched": false,
      "enriched_at": "2026-02-03T11:53:15.052Z",
      "priority": "high",
      "priority_reasons": [
        "100+ people/units",
        "24/7 or captive audience"
      ],
      "enrich_score": 21
    },
    {
      "id": 26,
      "company": "Las Vegas Post Acute & Rehabilitation",
      "facility_type": "Skilled Nursing / Rehab",
      "address": "2832 S Maryland Pkwy, Las Vegas, NV 89109",
      "parent_system": "Independent",
      "bed_count": 79,
      "contact_name": "Administrator",
      "contact_title": "Facility Administrator",
      "email": null,
      "email_status": "needs_research",
      "phone": "(702) 735-5848",
      "linkedin": null,
      "employee_count": "60-100",
      "vending_score": "A",
      "notes": "CMS Medicare data: 79 beds, 4-star overall rating, 5-star health inspection. Near Sunrise Hospital on Maryland Pkwy. Independent operator = no corporate red tape. Call main line and ask for administrator.",
      "priority": "high",
      "priority_reasons": [
        "100+ people/units",
        "24/7 or captive audience",
        "portfolio / multi-property leverage"
      ],
      "enrich_score": 31
    },
    {
      "id": 27,
      "company": "El Jen Skilled Care",
      "facility_type": "Skilled Nursing Facility",
      "address": "5538 W Duncan Dr, Las Vegas, NV 89130",
      "parent_system": "Empres / Evergreen",
      "bed_count": 144,
      "contact_name": "Administrator",
      "contact_title": "Facility Administrator",
      "email": null,
      "email_status": "needs_research",
      "phone": "(702) 645-2606",
      "linkedin": null,
      "employee_count": "100-150",
      "vending_score": "A",
      "notes": "CMS data: 144 beds, part of Empres/Evergreen chain (42 facilities). 24/7 staff operations. Large facility = multiple vending placement opportunities. Chain operator = if we win one, could scale to 42 locations.",
      "priority": "high",
      "priority_reasons": [
        "150+ people/units",
        "24/7 or captive audience",
        "chain gateway (42+ locations)"
      ],
      "enrich_score": 52
    },
    {
      "id": 28,
      "company": "VA Southern Nevada Healthcare System",
      "facility_type": "VA Medical Center",
      "address": "6900 N Pecos Rd, North Las Vegas, NV 89086",
      "parent_system": "U.S. Department of Veterans Affairs",
      "bed_count": 150,
      "contact_name": "William J. Caron",
      "contact_title": "Director/CEO",
      "email": null,
      "email_status": "domain_only",
      "phone": "(702) 791-9000",
      "linkedin": null,
      "employee_count": "2000-3000",
      "vending_score": "A+",
      "notes": "Named in NHA press release as VASNHS Director/CEO. VA hospitals are federal = may require GSA/Randolph-Sheppard process. But massive foot traffic and 24/7 operations. Email domain: @va.gov. Vending may be handled by canteen service.",
      "apollo_enriched": false,
      "enriched_at": "2026-02-03T11:53:15.389Z",
      "priority": "high",
      "priority_reasons": [
        "3000+ people/units",
        "24/7 or captive audience"
      ],
      "enrich_score": 50
    },
    {
      "id": 29,
      "company": "Sunrise of Henderson (Senior Living)",
      "facility_type": "Assisted Living / Memory Care",
      "address": "1555 W Horizon Ridge Pkwy, Henderson, NV 89012",
      "parent_system": "Sunrise Senior Living",
      "bed_count": 120,
      "contact_name": "Executive Director",
      "contact_title": "Executive Director",
      "email": null,
      "email_status": "domain_only",
      "phone": "(702) 614-1500",
      "linkedin": null,
      "employee_count": "60-80",
      "vending_score": "A",
      "notes": "Henderson location. 4.4 stars on Caring.com. Sunrise Senior Living is a major national brand. Staff + visitors + mobile residents. Email domain: @sunriseseniorliving.com",
      "apollo_enriched": false,
      "enriched_at": "2026-02-03T11:53:15.728Z",
      "priority": "high",
      "priority_reasons": [
        "120+ people/units"
      ],
      "enrich_score": 11
    },
    {
      "id": 30,
      "company": "Silver Hills Health Care Center",
      "facility_type": "Skilled Nursing Facility",
      "address": "3450 N Buffalo Dr, Las Vegas, NV 89129",
      "parent_system": "Independent",
      "bed_count": 155,
      "contact_name": "Administrator",
      "contact_title": "Facility Administrator",
      "email": null,
      "email_status": "needs_research",
      "phone": "(702) 749-6400",
      "linkedin": null,
      "employee_count": "100-150",
      "vending_score": "A",
      "notes": "155-bed SNF. Staff working 24/7 shifts = high vending demand especially nights/weekends when cafeteria closed. Break room placement is key.",
      "priority": "high",
      "priority_reasons": [
        "155+ people/units",
        "24/7 or captive audience"
      ],
      "enrich_score": 22
    },
    {
      "id": 31,
      "company": "Royal Springs Healthcare and Rehab",
      "facility_type": "Skilled Nursing / Rehab",
      "address": "8501 Del Webb Blvd, Las Vegas, NV 89134",
      "parent_system": "Independent",
      "bed_count": 225,
      "contact_name": "Director of Operations",
      "contact_title": "Administrator / Director of Operations",
      "email": null,
      "email_status": "needs_research",
      "phone": "(702) 243-5600",
      "linkedin": null,
      "employee_count": "150-200",
      "vending_score": "A",
      "notes": "225 rooms - one of the largest SNFs in the area. Del Webb / Summerlin area = upscale. Established 2006. Multiple machine placement opportunities.",
      "priority": "high",
      "priority_reasons": [
        "225+ people/units"
      ],
      "enrich_score": 12
    }
  ],
  "summary": {
    "total_leads": 31,
    "leads_with_verified_emails": 3,
    "leads_with_pattern_confirmed_emails": 6,
    "leads_with_confirmed_vendor_contact_emails": 5,
    "leads_with_linkedin_profiles": 12,
    "leads_needing_email_research": 15,
    "facility_types": {
      "hospitals": 14,
      "dialysis_centers": 3,
      "senior_living_nursing": 11,
      "rehab_facilities": 2,
      "va_medical_center": 1
    },
    "priority_targets": [
      "UMC - Stephanie Ortiz (verified email, direct facilities contact)",
      "UMC - Michael Langley (verified email, facilities operations)",
      "Valley Health System - NVCBO@uhsinc.com (verified, gates 6+ hospitals)",
      "West Henderson Hospital (NEW facility, no vendor yet, Henderson location)",
      "Alorah Healthcare (NEW BUILD SNF, no vendor yet, Henderson)",
      "Seven Hills BH (Henderson, hiring new Director of Facility Ops)",
      "DaVita - Wesley Molden (pattern confirmed, gates 15+ dialysis centers)"
    ]
  },
  "outreach_strategy": {
    "tier1_immediate": [
      "Email Stephanie Ortiz at UMC re: smart market for staff break rooms and waiting areas",
      "Email NVCBO@uhsinc.com to start Valley Health System vendor approval process",
      "Pop-in at West Henderson Hospital (new facility, Henderson, no vendor)",
      "Pop-in at Seven Hills BH (Henderson, new facility director being hired)",
      "Email Wesley Molden at DaVita re: vending for dialysis waiting areas"
    ],
    "tier2_this_week": [
      "Call UMC main line, ask for Director of Facilities by name",
      "Visit Dan Hills at Alorah Healthcare new build site",
      "Call Henderson Hospital and ask for local facilities contact",
      "Email DaVita Group FAs (Angela Weinstock, Laurence Fortes)"
    ],
    "tier3_this_month": [
      "Research HCA Healthcare local contacts at Sunrise/MountainView/Southern Hills",
      "Visit senior living facilities in person with gift baskets",
      "Register as vendor with Clark County for UMC public bid process",
      "Contact VA canteen service for VASNHS opportunity"
    ],
    "pitch_angle": "Modern AI-powered smart market with healthy options for staff wellness, cashless payment, guaranteed 24/7 uptime with local service commitment. We're local - you can call us anytime.",
    "key_insight": "Valley Health System (UHS) = 6 hospitals + 1 new hospital + 7 freestanding ERs + treatment center. Single vendor relationship through NVCBO@uhsinc.com could yield 15+ locations. This is the WHALE account for healthcare."
  },
  "enrichment_run": "2026-02-03T11:53:15.930Z",
  "apollo_enriched_count": 0
}